setup.py
onename/__init__.py
onename/client.py
onename.egg-info/PKG-INFO
onename.egg-info/SOURCES.txt
onename.egg-info/dependency_links.txt
onename.egg-info/not-zip-safe
onename.egg-info/requires.txt
onename.egg-info/top_level.txt