Metadata-Version: 1.1
Name: onename
Version: 0.2.0
Summary: Onename API python client
Home-page: https://github.com/onenameio/onename-python
Author: Halfmoon Labs, Inc.
Author-email: hello@onename.com
License: MIT
Keywords: onename api identity blockchain
Platform: UNKNOWN
Classifier: Intended Audience :: Developers
Classifier: License :: OSI Approved :: MIT License
Classifier: Operating System :: OS Independent
Classifier: Programming Language :: Python
Classifier: Topic :: Internet
Classifier: Topic :: Software Development :: Libraries :: Python Modules
